dggbot/__init__.py
dggbot/_logging.py
dggbot/bot.py
dggbot/chat.py
dggbot/errors.py
dggbot/event.py
dggbot/flairs.py
dggbot/funcs.py
dggbot/message.py
dggbot/user.py
dggbot/wsbase.py
dggbot/live/__init__.py
dggbot/live/message.py
dgg_bot-1.9.0.dist-info/LICENSE
dgg_bot-1.9.0.dist-info/METADATA
dgg_bot-1.9.0.dist-info/WHEEL
dgg_bot-1.9.0.dist-info/top_level.txt
dgg_bot-1.9.0.dist-info/RECORD
