Metadata-Version: 2.1
Name: dgg-bot
Version: 1.9.0
Summary: A library for connecting to and making a bot in Destiny.gg chat.
Author: Fritz-02
License: MIT
Project-URL: Homepage, https://github.com/Fritz-02/dgg-bot/
Project-URL: Bug Tracker, https://github.com/Fritz-02/dgg-bot/issues
Classifier: Development Status :: 5 - Production/Stable
Classifier: License :: OSI Approved :: MIT License
Classifier: Operating System :: OS Independent
Classifier: Programming Language :: Python :: 3.9
Classifier: Programming Language :: Python :: 3.10
Classifier: Programming Language :: Python :: 3.11
Classifier: Topic :: Communications :: Chat
Requires-Python: >=3.9
License-File: LICENSE
Requires-Dist: requests==2.32.3
Requires-Dist: websocket-client>=1.8.0
Provides-Extra: dev
Requires-Dist: black; extra == "dev"
Requires-Dist: flake8; extra == "dev"
Requires-Dist: python-dotenv; extra == "dev"
